LICENSE
MANIFEST.in
README.rst
setup.cfg
setup.py
docar/__init__.py
docar/collections.py
docar/compat.py
docar/documents.py
docar/exceptions.py
docar/fields.py
docar/serializers.py
docar.egg-info/PKG-INFO
docar.egg-info/SOURCES.txt
docar.egg-info/dependency_links.txt
docar.egg-info/requires.txt
docar.egg-info/top_level.txt
docar/backends/__init__.py
docar/backends/django.py
docar/backends/http.py
docs/Makefile
docs/backends.rst
docs/conf.py
docs/documents.rst
docs/fields.rst
docs/index.rst
docs/make.bat
docs/mapping_fields.rst
docs/_build/doctrees/backends.doctree
docs/_build/doctrees/documents.doctree
docs/_build/doctrees/documents_and_collections.doctree
docs/_build/doctrees/environment.pickle
docs/_build/doctrees/fields.doctree
docs/_build/doctrees/index.doctree
docs/_build/doctrees/mapping_fields.doctree
docs/_build/html/.buildinfo
docs/_build/html/backends.html
docs/_build/html/documents.html
docs/_build/html/documents_and_collections.html
docs/_build/html/fields.html
docs/_build/html/genindex.html
docs/_build/html/index.html
docs/_build/html/mapping_fields.html
docs/_build/html/objects.inv
docs/_build/html/search.html
docs/_build/html/searchindex.js
docs/_build/html/_sources/backends.txt
docs/_build/html/_sources/documents.txt
docs/_build/html/_sources/documents_and_collections.txt
docs/_build/html/_sources/fields.txt
docs/_build/html/_sources/index.txt
docs/_build/html/_sources/mapping_fields.txt
docs/_build/html/_static/ajax-loader.gif
docs/_build/html/_static/basic.css
docs/_build/html/_static/comment-bright.png
docs/_build/html/_static/comment-close.png
docs/_build/html/_static/comment.png
docs/_build/html/_static/default.css
docs/_build/html/_static/doctools.js
docs/_build/html/_static/down-pressed.png
docs/_build/html/_static/down.png
docs/_build/html/_static/file.png
docs/_build/html/_static/jquery.js
docs/_build/html/_static/minus.png
docs/_build/html/_static/plus.png
docs/_build/html/_static/pygments.css
docs/_build/html/_static/searchtools.js
docs/_build/html/_static/sidebar.js
docs/_build/html/_static/underscore.js
docs/_build/html/_static/up-pressed.png
docs/_build/html/_static/up.png
