Metadata-Version: 1.1
Name: docar
Version: 0.9.1
Summary: Create resource oriented architectures for RESTful client and server applications.
Home-page: https://github.com/30loops/python-docar
Author: Christo Buschek
Author-email: crito@30loops.net
License: UNKNOWN
Platform: UNKNOWN
Classifier: Development Status :: 4 - Beta
Classifier: Environment :: Web Environment
Classifier: Intended Audience :: Developers
Classifier: License :: OSI Approved :: BSD License
Classifier: Operating System :: OS Independent
Classifier: Programming Language :: Python
Classifier: Programming Language :: Python :: 3
Classifier: Topic :: Internet :: WWW/HTTP
